media/img/precisetimer_macos_1000ms.png
media/img/precisetimer_macos_100ms.png
media/img/precisetimer_macos_10ms.png
media/img/precisetimer_macos_1ms.png
media/img/precisetimer_macos_40ms.png
media/img/precisetimer_windows_1000ms.png
media/img/precisetimer_windows_100ms.png
media/img/precisetimer_windows_10ms.png
media/img/precisetimer_windows_1ms.png
media/img/precisetimer_windows_40ms.png
media/img/ribosome.png
media/img/timer_interval_exceeded.png
media/img/timer_macos_1000ms.png
media/img/timer_macos_100ms.png
media/img/timer_macos_10ms.png
media/img/timer_macos_1ms.png
media/img/timer_macos_40ms.png
media/img/timer_windows_1000ms.png
media/img/timer_windows_100ms.png
media/img/timer_windows_10ms.png
media/img/timer_windows_1ms.png
media/img/timer_windows_40ms.png
oclock/__init__.py
oclock/__main__.py
oclock/countdown.py
oclock/event.py
oclock/general.py
oclock/loop.py
oclock/performance.py
oclock/timer.py
tests/test_oclock.py
oclock-1.4.2.dist-info/LICENSE
oclock-1.4.2.dist-info/METADATA
oclock-1.4.2.dist-info/WHEEL
oclock-1.4.2.dist-info/top_level.txt
oclock-1.4.2.dist-info/RECORD
