Metadata-Version: 2.2
Name: oclock
Version: 1.4.2
Summary:  Tools for timed, no-drift loops of constant duration, and other misc. timing tools (GUI countdown, context managers etc.)
Author-email: Olivier Vincent <ovinc.py@gmail.com>
License: GNU GPLv3
Project-URL: Homepage, https://github.com/ovinc/oclock
Project-URL: Documentation, https://github.com/ovinc/oclock/README.md
Project-URL: Repository, https://github.com/ovinc/oclock.git
Keywords: timing,loops,constant duration,cancellable,modifiable,countdown,context manager,gui
Classifier: Programming Language :: Python :: 3
Classifier: Operating System :: OS Independent
Classifier: License :: OSI Approved :: GNU General Public License v3 or later (GPLv3+)
Requires-Python: >=3.5
License-File: LICENSE
Requires-Dist: importlib-metadata
